ttslib/__init__.py
ttslib/core.py
ttslib/data/__init__.py
ttslib/data/espeak.yaml
ttslib/data/guess.yaml
ttslib/data/osx.txt
ttslib/data/speaker.yaml
ttslib/data/supported.yaml
ttslib/data/to_speaker.yaml
ttslib/data/windows.yaml
ttslib/guess.py
ttslib/osx.py
ttslib/ttsx.py
ttslib/util.py
ttslib-0.1.1.1.dist-info/LICENSE
ttslib-0.1.1.1.dist-info/WHEEL
ttslib-0.1.1.1.dist-info/METADATA
ttslib-0.1.1.1.dist-info/RECORD
