Metadata-Version: 2.1
Name: ttslib
Version: 0.1.1.1
Summary: TTS for local usage that works for all OS's, with a simple interface
Home-page: UNKNOWN
License: MIT
Author: Pacharapol Withayasakpunt
Author-email: patarapolw@gmail.com
Classifier: License :: OSI Approved :: MIT License
Classifier: Programming Language :: Python :: 2
Classifier: Programming Language :: Python :: 2.7
Classifier: Programming Language :: Python :: 3
Classifier: Programming Language :: Python :: 3.4
Classifier: Programming Language :: Python :: 3.5
Classifier: Programming Language :: Python :: 3.6
Classifier: Programming Language :: Python :: 3.7
Requires-Dist: importlib_resources (>=1.0,<2.0)
Requires-Dist: pyttsx3 (>=2.7,<3.0)
Requires-Dist: ruamel.yaml (>=0.15.74,<0.16.0)
